guardianhub/__init__.py
guardianhub/_version.py
guardianhub/agents/AgentDesign.md
guardianhub/agents/README.md
guardianhub/agents/runtime.py
guardianhub/agents/services/episodic_manager.py
guardianhub/agents/services/memory_manager.py
guardianhub/agents/specialist_base.py
guardianhub/agents/workflows/__init__.py
guardianhub/agents/workflows/agent_contract.py
guardianhub/agents/workflows/constants.py
guardianhub/agents/workflows/mission_skeleton.py
guardianhub/agents/workflows/muscle_factory.py
guardianhub/auth/token_provider.py
guardianhub/clients/__init__.py
guardianhub/clients/a2a_client.py
guardianhub/clients/classification_client.py
guardianhub/clients/consul_client.py
guardianhub/clients/graph_db_client.py
guardianhub/clients/langfuse/dataset_client.py
guardianhub/clients/langfuse/manager.py
guardianhub/clients/langfuse/prompt_client.py
guardianhub/clients/langfuse/score_evaluation_client.py
guardianhub/clients/langfuse/tracing_client.py
guardianhub/clients/langfuse_client.py
guardianhub/clients/llm_client.py
guardianhub/clients/llm_worker.py
guardianhub/clients/ocr_client.py
guardianhub/clients/paperless_client.py
guardianhub/clients/text_cleaner_client.py
guardianhub/clients/tool_registry_client.py
guardianhub/clients/vector_client.py
guardianhub/config/__init__.py
guardianhub/config/config_development.json
guardianhub/config/config_prod.json
guardianhub/config/settings.py
guardianhub/http/http_client.py
guardianhub/logging/__init__.py
guardianhub/logging/logging.py
guardianhub/logging/logging_filters.py
guardianhub/models/__init__.py
guardianhub/models/agent/__init__.py
guardianhub/models/agent/contracts/__init__.py
guardianhub/models/agent/contracts/action.py
guardianhub/models/agent/contracts/attainment.py
guardianhub/models/agent/contracts/base.py
guardianhub/models/agent/contracts/completion.py
guardianhub/models/agent/contracts/debrief.py
guardianhub/models/agent/contracts/discovery.py
guardianhub/models/agent/contracts/history.py
guardianhub-0.1.212.dist-info/METADATA
guardianhub-0.1.212.dist-info/WHEEL
guardianhub-0.1.212.dist-info/licenses/LICENSE
guardianhub-0.1.212.dist-info/RECORD
