Metadata-Version: 2.4
Name: guardianhub
Version: 0.1.212
Summary: Unified SDK for Local AI Guardian
License: MIT
License-File: LICENSE
Author: Jayant
Author-email: jayant@yantramops.com
Requires-Python: >=3.10
Classifier: License :: OSI Approved :: MIT License
Classifier: Programming Language :: Python :: 3
Classifier: Programming Language :: Python :: 3.10
Classifier: Programming Language :: Python :: 3.11
Classifier: Programming Language :: Python :: 3.12
Classifier: Programming Language :: Python :: 3.13
Classifier: Programming Language :: Python :: 3.14
Provides-Extra: dev
Provides-Extra: muscle
Provides-Extra: test
Requires-Dist: click (>=8.0.0)
Requires-Dist: fastapi (>=0.123.0)
Requires-Dist: httpcore (>=0.17.0)
Requires-Dist: httpx (>=0.24.0)
Requires-Dist: langfuse (==3.10.1) ; python_version >= "3.10" and python_version < "4.0"
Requires-Dist: opentelemetry-api (>=1.38.0)
Requires-Dist: opentelemetry-exporter-otlp-proto-http (>=1.38.0)
Requires-Dist: opentelemetry-instrumentation-fastapi (>=0.59b0)
Requires-Dist: opentelemetry-instrumentation-httpx (>=0.59b0)
Requires-Dist: opentelemetry-sdk (>=1.38.0)
Requires-Dist: opentelemetry-util-http (>=0.59b0)
Requires-Dist: prometheus-client (>=0.23.1)
Requires-Dist: pycryptodome (>=3.18.0)
Requires-Dist: pydantic (>=2.0.0)
Requires-Dist: pydantic-settings (>=2.0.0)
Requires-Dist: pytest (>=7.0.0) ; extra == "dev"
Requires-Dist: pytest (>=7.0.0) ; extra == "test"
Requires-Dist: pytest-asyncio (>=0.20.0) ; extra == "dev"
Requires-Dist: pytest-asyncio (>=0.20.0) ; extra == "test"
Requires-Dist: pytest-cov (>=4.0.0) ; extra == "dev"
Requires-Dist: pytest-cov (>=4.0.0) ; extra == "test"
Requires-Dist: pytest-httpx (>=0.25.0) ; extra == "dev"
Requires-Dist: pytest-httpx (>=0.25.0) ; extra == "test"
Requires-Dist: pytest-mock (>=3.10.0) ; extra == "dev"
Requires-Dist: pytest-mock (>=3.10.0) ; extra == "test"
Requires-Dist: temporalio (>=1.5.0) ; extra == "muscle"
Requires-Dist: uvicorn (>=0.23.0) ; extra == "muscle"
Project-URL: Homepage, https://github.com/yantramai/guardianhub-sdk
Project-URL: Source, https://github.com/yantramai/guardianhub-sdk
